thingsboard_gateway/__init__.py
thingsboard_gateway/tb_gateway.py
thingsboard_gateway/version.py
thingsboard_gateway/config/1.json
thingsboard_gateway/config/356T.json
thingsboard_gateway/config/4T.json
thingsboard_gateway/config/5.json
thingsboard_gateway/config/EDE.csv
thingsboard_gateway/config/as.json
thingsboard_gateway/config/b.json
thingsboard_gateway/config/bacnet.json
thingsboard_gateway/config/bacnet1.json
thingsboard_gateway/config/ble.json
thingsboard_gateway/config/c.json
thingsboard_gateway/config/ca.pem
thingsboard_gateway/config/can.json
thingsboard_gateway/config/connected_devices.json
thingsboard_gateway/config/custom_serial.json
thingsboard_gateway/config/dfv.json
thingsboard_gateway/config/ftp.json
thingsboard_gateway/config/g.json
thingsboard_gateway/config/gatewayConnector.json
thingsboard_gateway/config/gh.json
thingsboard_gateway/config/knx.json
thingsboard_gateway/config/list.json
thingsboard_gateway/config/logs.json
thingsboard_gateway/config/m.json
thingsboard_gateway/config/modbus.json
thingsboard_gateway/config/modbusD.json
thingsboard_gateway/config/modbus_async.json
thingsboard_gateway/config/modbus_energy.json
thingsboard_gateway/config/modbus_serial.json
thingsboard_gateway/config/mqtt.json
thingsboard_gateway/config/ocpp.json
thingsboard_gateway/config/odbc.json
thingsboard_gateway/config/opcOld.json
thingsboard_gateway/config/opcua.json
thingsboard_gateway/config/opcua10K.json
thingsboard_gateway/config/opcuaBAsic.json
thingsboard_gateway/config/opcuaNewAdvanced.json
thingsboard_gateway/config/r.json
thingsboard_gateway/config/request.json
thingsboard_gateway/config/rest.json
thingsboard_gateway/config/rf.json
thingsboard_gateway/config/s.json
thingsboard_gateway/config/sdf.json
thingsboard_gateway/config/sdg43.json
thingsboard_gateway/config/snmp.json
thingsboard_gateway/config/socket.json
thingsboard_gateway/config/statistics.json
thingsboard_gateway/config/superOpc.json
thingsboard_gateway/config/tb_gateway.json
thingsboard_gateway-3.8.1.dist-info/licenses/LICENSE
thingsboard_gateway-3.8.1.dist-info/METADATA
thingsboard_gateway-3.8.1.dist-info/WHEEL
thingsboard_gateway-3.8.1.dist-info/entry_points.txt
thingsboard_gateway-3.8.1.dist-info/top_level.txt
thingsboard_gateway-3.8.1.dist-info/RECORD
