Metadata-Version: 2.4
Name: thingsboard-gateway
Version: 3.8.1
Summary: Thingsboard Gateway for IoT devices.
Home-page: https://github.com/thingsboard/thingsboard-gateway
Download-URL: https://github.com/thingsboard/thingsboard-gateway/archive/3.8.1.tar.gz
Author: ThingsBoard
Author-email: info@thingsboard.io
License: Apache Software License (Apache Software License 2.0)
Requires-Python: >=3.10
License-File: LICENSE
Requires-Dist: setuptools
Requires-Dist: cryptography
Requires-Dist: jsonpath-rw
Requires-Dist: regex
Requires-Dist: pip
Requires-Dist: PyYAML
Requires-Dist: orjson
Requires-Dist: pybase64
Requires-Dist: simplejson
Requires-Dist: urllib3>=2.3.0
Requires-Dist: requests>=2.32.3
Requires-Dist: mmh3
Requires-Dist: grpcio
Requires-Dist: protobuf
Requires-Dist: python-dateutil
Requires-Dist: cachetools
Requires-Dist: tb-paho-mqtt-client>=2.1.2
Requires-Dist: tb-mqtt-client==1.13.12
Requires-Dist: packaging==23.1
Requires-Dist: service-identity
Requires-Dist: psutil
Requires-Dist: PySocks
Dynamic: author
Dynamic: author-email
Dynamic: description
Dynamic: description-content-type
Dynamic: download-url
Dynamic: home-page
Dynamic: license
Dynamic: license-file
Dynamic: requires-dist
Dynamic: requires-python
Dynamic: summary
